metatrader_client/__init__.py
metatrader_client/_types.py
metatrader_client/client.py
metatrader_client/client_account.py
metatrader_client/client_connection.py
metatrader_client/client_history.py
metatrader_client/client_market.py
metatrader_client/client_order.py
metatrader_client/exceptions.py
metatrader_client/utils.py
metatrader_client/account/__init__.py
metatrader_client/account/check_margin_level.py
metatrader_client/account/get_account_info.py
metatrader_client/account/get_account_type.py
metatrader_client/account/get_balance.py
metatrader_client/account/get_currency.py
metatrader_client/account/get_equity.py
metatrader_client/account/get_free_margin.py
metatrader_client/account/get_leverage.py
metatrader_client/account/get_margin.py
metatrader_client/account/get_margin_level.py
metatrader_client/account/get_trade_statistics.py
metatrader_client/account/is_trade_allowed.py
metatrader_client/connection/__init__.py
metatrader_client/connection/_ensure_cooldown.py
metatrader_client/connection/_find_terminal_path.py
metatrader_client/connection/_get_last_error.py
metatrader_client/connection/_initialize_terminal.py
metatrader_client/connection/_login.py
metatrader_client/connection/connect.py
metatrader_client/connection/disconnect.py
metatrader_client/connection/get_terminal_info.py
metatrader_client/connection/get_version.py
metatrader_client/connection/is_connected.py
metatrader_client/history/__init__.py
metatrader_client/history/get_deals.py
metatrader_client/history/get_deals_as_dataframe.py
metatrader_client/history/get_orders.py
metatrader_client/history/get_orders_as_dataframe.py
metatrader_client/history/get_total_deals.py
metatrader_client/history/get_total_orders.py
metatrader_client/market/__init__.py
metatrader_client/market/get_candles_by_date.py
metatrader_client/market/get_candles_latest.py
metatrader_client/market/get_symbol_info.py
metatrader_client/market/get_symbol_price.py
metatrader_client/market/get_symbols.py
metatrader_mcp_server-0.2.9.dist-info/licenses/LICENSE
metatrader_mcp_server-0.2.9.dist-info/METADATA
metatrader_mcp_server-0.2.9.dist-info/WHEEL
metatrader_mcp_server-0.2.9.dist-info/entry_points.txt
metatrader_mcp_server-0.2.9.dist-info/top_level.txt
metatrader_mcp_server-0.2.9.dist-info/RECORD
